[{"title":"キングダム 用語集","series":"キングダム","date":"2025-11-10T06:43:25Z","url":"https://pontarou0610.github.io/manga-kousatsu-hub/posts/2025/11/%E3%82%AD%E3%83%B3%E3%82%B0%E3%83%80%E3%83%A0-%E7%94%A8%E8%AA%9E%E9%9B%86/","tags":["用語解説","週刊誌","用語解説","歴史","バトル"]},{"title":"スキップとローファー 用語集","series":"スキップとローファー","date":"2025-11-10T06:43:25Z","url":"https://pontarou0610.github.io/manga-kousatsu-hub/posts/2025/11/%E3%82%B9%E3%82%AD%E3%83%83%E3%83%97%E3%81%A8%E3%83%AD%E3%83%BC%E3%83%95%E3%82%A1%E3%83%BC-%E7%94%A8%E8%AA%9E%E9%9B%86/","tags":["用語解説","用語解説","青春","日常","月刊誌"]},{"title":"デッドマウント・デスプレイ 用語集","series":"デッドマウント・デスプレイ","date":"2025-11-10T06:43:25Z","url":"https://pontarou0610.github.io/manga-kousatsu-hub/posts/2025/11/%E3%83%87%E3%83%83%E3%83%89%E3%83%9E%E3%82%A6%E3%83%B3%E3%83%88%E3%83%87%E3%82%B9%E3%83%97%E3%83%AC%E3%82%A4-%E7%94%A8%E8%AA%9E%E9%9B%86/","tags":["用語解説","月刊誌","用語解説","バトル","ダークファンタジー"]},{"title":"宇宙兄弟 用語集","series":"宇宙兄弟","date":"2025-11-10T06:43:25Z","url":"https://pontarou0610.github.io/manga-kousatsu-hub/posts/2025/11/%E5%AE%87%E5%AE%99%E5%85%84%E5%BC%9F-%E7%94%A8%E8%AA%9E%E9%9B%86/","tags":["用語解説","宇宙","用語解説","ヒューマンドラマ","月刊誌"]},{"title":"天国大魔境 用語集","series":"天国大魔境","date":"2025-11-10T06:43:25Z","url":"https://pontarou0610.github.io/manga-kousatsu-hub/posts/2025/11/%E5%A4%A9%E5%9B%BD%E5%A4%A7%E9%AD%94%E5%A2%83-%E7%94%A8%E8%AA%9E%E9%9B%86/","tags":["用語解説","ミステリー","用語解説","SF","月刊誌"]},{"title":"薬屋のひとりごと 用語集","series":"薬屋のひとりごと","date":"2025-11-10T06:43:25Z","url":"https://pontarou0610.github.io/manga-kousatsu-hub/posts/2025/11/%E8%96%AC%E5%B1%8B%E3%81%AE%E3%81%B2%E3%81%A8%E3%82%8A%E3%81%94%E3%81%A8-%E7%94%A8%E8%AA%9E%E9%9B%86/","tags":["用語解説","宮廷劇","歴史ミステリー","用語解説","月刊誌"]}]